trackmaster/__init__.py
trackmaster/raw.py
trackmaster/treadmill.py
trackmaster-0.1.1.dist-info/DESCRIPTION.rst
trackmaster-0.1.1.dist-info/METADATA
trackmaster-0.1.1.dist-info/RECORD
trackmaster-0.1.1.dist-info/WHEEL
trackmaster-0.1.1.dist-info/metadata.json
trackmaster-0.1.1.dist-info/top_level.txt
