Metadata-Version: 1.1
Name: trackmaster
Version: 0.1.1
Summary: Interface for controlling Trackmaster treadmills
Home-page: https://github.com/hsharrison/trackmaster-python
Author: Henry S. Harrison
Author-email: henry.schafer.harrison@gmail.com
License: MIT
Download-URL: https://github.com/hsharrison/trackmaster-python/archive/master.zip
Keywords: treadmill trackmaster serial
Platform: UNKNOWN
Classifier: Programming Language :: Python
Classifier: Programming Language :: Python :: 2
Classifier: Programming Language :: Python :: 3
Classifier: License :: OSI Approved :: MIT License
Classifier: Operating System :: OS Independent
Classifier: Development Status :: 3 - Alpha
Classifier: Intended Audience :: Science/Research
Classifier: Topic :: Utilities
Classifier: Topic :: Scientific/Engineering
